setup.cfg
setup.py
he_update/__init__.py
he_update.egg-info/PKG-INFO
he_update.egg-info/SOURCES.txt
he_update.egg-info/dependency_links.txt
he_update.egg-info/entry_points.txt
he_update.egg-info/pbr.json
he_update.egg-info/requires.txt
he_update.egg-info/top_level.txt