Metadata-Version: 1.1
Name: he-update
Version: 1.1
Summary: Hurricane Electric tunnel endpoint and dyndns updater
Home-page: https://github.com/joejulian/he-update
Author: Joe Julian
Author-email: me@joejulian.name
License: UNKNOWN
Download-URL: https://github.com/joejulian/he-update/tarball/v1.1
Keywords: tunnel,ipv6,dyndns,Hurricane,update
Platform: UNKNOWN
Classifier: Development Status :: 5 - Production/Stable
Classifier: Environment :: Console
Classifier: Intended Audience :: System Administrators
Classifier: License :: OSI Approved :: GNU General Public License v3 (GPLv3)
Classifier: Programming Language :: Python
Classifier: Topic :: Internet :: Name Service (DNS)
Classifier: Topic :: System :: Networking
Classifier: Topic :: Utilities
